{
    "theme-name": "classic-white_theme",
    "type": "portal",
    "templates": [
        "404",
        "about",
        "category",
        "index",
        "maintenance",
        "news",
        "page",
        "post",
        "reviews",
        "streams",
        "tech",
        "videos"
    ],
    "styles": {        
            "white-classic-2015": {},
            "white-classic-full-2015": {},
            "black-classic-2015": {},
            "black-classic-full-2015": {},
            "black-modern-full-2015": {}
    },
    "config": {
            
    }
    
}